{
    "description": "TYPE: CUSTOM\nMaterial Theme Builder export 2024-05-21 09:53:20",
    "seed": "#E8C868",
    "coreColors": {
        "primary": "#E8C868"
    },
    "extendedColors": [],
    "schemes": {
        "light": {
            "primary": "#725C0C",
            "surfaceTint": "#725C0C",
            "onPrimary": "#FFFFFF",
            "primaryContainer": "#FFE086",
            "onPrimaryContainer": "#231A00",
            "secondary": "#685D3F",
            "onSecondary": "#FFFFFF",
            "secondaryContainer": "#F1E1BB",
            "onSecondaryContainer": "#221B04",
            "tertiary": "#46664B",
            "onTertiary": "#FFFFFF",
            "tertiaryContainer": "#C8ECCA",
            "onTertiaryContainer": "#02210C",
            "error": "#BA1A1A",
            "onError": "#FFFFFF",
            "errorContainer": "#FFDAD6",
            "onErrorContainer": "#410002",
            "background": "#FFF8F0",
            "onBackground": "#1F1B13",
            "surface": "#FFF8F0",
            "onSurface": "#1F1B13",
            "surfaceVariant": "#EBE1CF",
            "onSurfaceVariant": "#4C4639",
            "outline": "#7D7667",
            "outlineVariant": "#CEC6B4",
            "shadow": "#000000",
            "scrim": "#000000",
            "inverseSurface": "#343027",
            "inverseOnSurface": "#F8F0E2",
            "inversePrimary": "#E2C46D",
            "primaryFixed": "#FFE086",
            "onPrimaryFixed": "#231A00",
            "primaryFixedDim": "#E2C46D",
            "onPrimaryFixedVariant": "#574500",
            "secondaryFixed": "#F1E1BB",
            "onSecondaryFixed": "#221B04",
            "secondaryFixedDim": "#D4C5A1",
            "onSecondaryFixedVariant": "#50462A",
            "tertiaryFixed": "#C8ECCA",
            "onTertiaryFixed": "#02210C",
            "tertiaryFixedDim": "#ACCFAF",
            "onTertiaryFixedVariant": "#2F4E35",
            "surfaceDim": "#E1D9CC",
            "surfaceBright": "#FFF8F0",
            "surfaceContainerLowest": "#FFFFFF",
            "surfaceContainerLow": "#FBF3E5",
            "surfaceContainer": "#F5EDDF",
            "surfaceContainerHigh": "#EFE7D9",
            "surfaceContainerHighest": "#EAE2D4"
        },
        "light-medium-contrast": {
            "primary": "#524100",
            "surfaceTint": "#725C0C",
            "onPrimary": "#FFFFFF",
            "primaryContainer": "#8A7223",
            "onPrimaryContainer": "#FFFFFF",
            "secondary": "#4C4226",
            "onSecondary": "#FFFFFF",
            "secondaryContainer": "#807454",
            "onSecondaryContainer": "#FFFFFF",
            "tertiary": "#2B4931",
            "onTertiary": "#FFFFFF",
            "tertiaryContainer": "#5C7C60",
            "onTertiaryContainer": "#FFFFFF",
            "error": "#8C0009",
            "onError": "#FFFFFF",
            "errorContainer": "#DA342E",
            "onErrorContainer": "#FFFFFF",
            "background": "#FFF8F0",
            "onBackground": "#1F1B13",
            "surface": "#FFF8F0",
            "onSurface": "#1F1B13",
            "surfaceVariant": "#EBE1CF",
            "onSurfaceVariant": "#484235",
            "outline": "#655E50",
            "outlineVariant": "#817A6B",
            "shadow": "#000000",
            "scrim": "#000000",
            "inverseSurface": "#343027",
            "inverseOnSurface": "#F8F0E2",
            "inversePrimary": "#E2C46D",
            "primaryFixed": "#8A7223",
            "onPrimaryFixed": "#FFFFFF",
            "primaryFixedDim": "#6F5A09",
            "onPrimaryFixedVariant": "#FFFFFF",
            "secondaryFixed": "#807454",
            "onSecondaryFixed": "#FFFFFF",
            "secondaryFixedDim": "#665B3D",
            "onSecondaryFixedVariant": "#FFFFFF",
            "tertiaryFixed": "#5C7C60",
            "onTertiaryFixed": "#FFFFFF",
            "tertiaryFixedDim": "#446349",
            "onTertiaryFixedVariant": "#FFFFFF",
            "surfaceDim": "#E1D9CC",
            "surfaceBright": "#FFF8F0",
            "surfaceContainerLowest": "#FFFFFF",
            "surfaceContainerLow": "#FBF3E5",
            "surfaceContainer": "#F5EDDF",
            "surfaceContainerHigh": "#EFE7D9",
            "surfaceContainerHighest": "#EAE2D4"
        },
        "light-high-contrast": {
            "primary": "#2B2100",
            "surfaceTint": "#725C0C",
            "onPrimary": "#FFFFFF",
            "primaryContainer": "#524100",
            "onPrimaryContainer": "#FFFFFF",
            "secondary": "#292109",
            "onSecondary": "#FFFFFF",
            "secondaryContainer": "#4C4226",
            "onSecondaryContainer": "#FFFFFF",
            "tertiary": "#092812",
            "onTertiary": "#FFFFFF",
            "tertiaryContainer": "#2B4931",
            "onTertiaryContainer": "#FFFFFF",
            "error": "#4E0002",
            "onError": "#FFFFFF",
            "errorContainer": "#8C0009",
            "onErrorContainer": "#FFFFFF",
            "background": "#FFF8F0",
            "onBackground": "#1F1B13",
            "surface": "#FFF8F0",
            "onSurface": "#000000",
            "surfaceVariant": "#EBE1CF",
            "onSurfaceVariant": "#282418",
            "outline": "#484235",
            "outlineVariant": "#484235",
            "shadow": "#000000",
            "scrim": "#000000",
            "inverseSurface": "#343027",
            "inverseOnSurface": "#FFFFFF",
            "inversePrimary": "#FFEBB6",
            "primaryFixed": "#524100",
            "onPrimaryFixed": "#FFFFFF",
            "primaryFixedDim": "#382B00",
            "onPrimaryFixedVariant": "#FFFFFF",
            "secondaryFixed": "#4C4226",
            "onSecondaryFixed": "#FFFFFF",
            "secondaryFixedDim": "#342C12",
            "onSecondaryFixedVariant": "#FFFFFF",
            "tertiaryFixed": "#2B4931",
            "onTertiaryFixed": "#FFFFFF",
            "tertiaryFixedDim": "#14331C",
            "onTertiaryFixedVariant": "#FFFFFF",
            "surfaceDim": "#E1D9CC",
            "surfaceBright": "#FFF8F0",
            "surfaceContainerLowest": "#FFFFFF",
            "surfaceContainerLow": "#FBF3E5",
            "surfaceContainer": "#F5EDDF",
            "surfaceContainerHigh": "#EFE7D9",
            "surfaceContainerHighest": "#EAE2D4"
        },
        "dark": {
            "primary": "#E2C46D",
            "surfaceTint": "#E2C46D",
            "onPrimary": "#3C2F00",
            "primaryContainer": "#574500",
            "onPrimaryContainer": "#FFE086",
            "secondary": "#D4C5A1",
            "onSecondary": "#383016",
            "secondaryContainer": "#50462A",
            "onSecondaryContainer": "#F1E1BB",
            "tertiary": "#ACCFAF",
            "onTertiary": "#183720",
            "tertiaryContainer": "#2F4E35",
            "onTertiaryContainer": "#C8ECCA",
            "error": "#FFB4AB",
            "onError": "#690005",
            "errorContainer": "#93000A",
            "onErrorContainer": "#FFDAD6",
            "background": "#16130B",
            "onBackground": "#EAE2D4",
            "surface": "#16130B",
            "onSurface": "#EAE2D4",
            "surfaceVariant": "#4C4639",
            "onSurfaceVariant": "#CEC6B4",
            "outline": "#989080",
            "outlineVariant": "#4C4639",
            "shadow": "#000000",
            "scrim": "#000000",
            "inverseSurface": "#EAE2D4",
            "inverseOnSurface": "#343027",
            "inversePrimary": "#725C0C",
            "primaryFixed": "#FFE086",
            "onPrimaryFixed": "#231A00",
            "primaryFixedDim": "#E2C46D",
            "onPrimaryFixedVariant": "#574500",
            "secondaryFixed": "#F1E1BB",
            "onSecondaryFixed": "#221B04",
            "secondaryFixedDim": "#D4C5A1",
            "onSecondaryFixedVariant": "#50462A",
            "tertiaryFixed": "#C8ECCA",
            "onTertiaryFixed": "#02210C",
            "tertiaryFixedDim": "#ACCFAF",
            "onTertiaryFixedVariant": "#2F4E35",
            "surfaceDim": "#16130B",
            "surfaceBright": "#3D392F",
            "surfaceContainerLowest": "#110E07",
            "surfaceContainerLow": "#1F1B13",
            "surfaceContainer": "#231F17",
            "surfaceContainerHigh": "#2D2A21",
            "surfaceContainerHighest": "#38342B"
        },
        "dark-medium-contrast": {
            "primary": "#E6C870",
            "surfaceTint": "#E2C46D",
            "onPrimary": "#1D1500",
            "primaryContainer": "#A88E3D",
            "onPrimaryContainer": "#000000",
            "secondary": "#D9CAA5",
            "onSecondary": "#1D1601",
            "secondaryContainer": "#9D906E",
            "onSecondaryContainer": "#000000",
            "tertiary": "#B0D4B3",
            "onTertiary": "#001B08",
            "tertiaryContainer": "#77997B",
            "onTertiaryContainer": "#000000",
            "error": "#FFBAB1",
            "onError": "#370001",
            "errorContainer": "#FF5449",
            "onErrorContainer": "#000000",
            "background": "#16130B",
            "onBackground": "#EAE2D4",
            "surface": "#16130B",
            "onSurface": "#FFFAF6",
            "surfaceVariant": "#4C4639",
            "onSurfaceVariant": "#D3CAB8",
            "outline": "#AAA291",
            "outlineVariant": "#8A8273",
            "shadow": "#000000",
            "scrim": "#000000",
            "inverseSurface": "#EAE2D4",
            "inverseOnSurface": "#2D2A21",
            "inversePrimary": "#584600",
            "primaryFixed": "#FFE086",
            "onPrimaryFixed": "#171000",
            "primaryFixedDim": "#E2C46D",
            "onPrimaryFixedVariant": "#433400",
            "secondaryFixed": "#F1E1BB",
            "onSecondaryFixed": "#171000",
            "secondaryFixedDim": "#D4C5A1",
            "onSecondaryFixedVariant": "#3E351B",
            "tertiaryFixed": "#C8ECCA",
            "onTertiaryFixed": "#001505",
            "tertiaryFixedDim": "#ACCFAF",
            "onTertiaryFixedVariant": "#1E3C25",
            "surfaceDim": "#16130B",
            "surfaceBright": "#3D392F",
            "surfaceContainerLowest": "#110E07",
            "surfaceContainerLow": "#1F1B13",
            "surfaceContainer": "#231F17",
            "surfaceContainerHigh": "#2D2A21",
            "surfaceContainerHighest": "#38342B"
        },
        "dark-high-contrast": {
            "primary": "#FFFAF6",
            "surfaceTint": "#E2C46D",
            "onPrimary": "#000000",
            "primaryContainer": "#E6C870",
            "onPrimaryContainer": "#000000",
            "secondary": "#FFFAF6",
            "onSecondary": "#000000",
            "secondaryContainer": "#D9CAA5",
            "onSecondaryContainer": "#000000",
            "tertiary": "#F0FFED",
            "onTertiary": "#000000",
            "tertiaryContainer": "#B0D4B3",
            "onTertiaryContainer": "#000000",
            "error": "#FFF9F9",
            "onError": "#000000",
            "errorContainer": "#FFBAB1",
            "onErrorContainer": "#000000",
            "background": "#16130B",
            "onBackground": "#EAE2D4",
            "surface": "#16130B",
            "onSurface": "#FFFFFF",
            "surfaceVariant": "#4C4639",
            "onSurfaceVariant": "#FFFAF6",
            "outline": "#D3CAB8",
            "outlineVariant": "#D3CAB8",
            "shadow": "#000000",
            "scrim": "#000000",
            "inverseSurface": "#EAE2D4",
            "inverseOnSurface": "#000000",
            "inversePrimary": "#352900",
            "primaryFixed": "#FFE59D",
            "onPrimaryFixed": "#000000",
            "primaryFixedDim": "#E6C870",
            "onPrimaryFixedVariant": "#1D1500",
            "secondaryFixed": "#F6E6BF",
            "onSecondaryFixed": "#000000",
            "secondaryFixedDim": "#D9CAA5",
            "onSecondaryFixedVariant": "#1D1601",
            "tertiaryFixed": "#CCF0CE",
            "onTertiaryFixed": "#000000",
            "tertiaryFixedDim": "#B0D4B3",
            "onTertiaryFixedVariant": "#001B08",
            "surfaceDim": "#16130B",
            "surfaceBright": "#3D392F",
            "surfaceContainerLowest": "#110E07",
            "surfaceContainerLow": "#1F1B13",
            "surfaceContainer": "#231F17",
            "surfaceContainerHigh": "#2D2A21",
            "surfaceContainerHighest": "#38342B"
        }
    },
    "palettes": {
        "primary": {
            "0": "#000000",
            "5": "#171000",
            "10": "#231A00",
            "15": "#302400",
            "20": "#3C2F00",
            "25": "#493A00",
            "30": "#574500",
            "35": "#655000",
            "40": "#735C00",
            "50": "#8E741C",
            "60": "#AA8E34",
            "70": "#C6A84C",
            "80": "#E3C464",
            "90": "#FFE086",
            "95": "#FFF0CB",
            "98": "#FFF8F0",
            "99": "#FFFBFF",
            "100": "#FFFFFF"
        },
        "secondary": {
            "0": "#000000",
            "5": "#161002",
            "10": "#211B08",
            "15": "#2C2511",
            "20": "#37301B",
            "25": "#433B25",
            "30": "#4E4630",
            "35": "#5A523A",
            "40": "#675E46",
            "50": "#80765D",
            "60": "#9B9075",
            "70": "#B6AA8E",
            "80": "#D2C5A8",
            "90": "#EFE1C3",
            "95": "#FDF0D0",
            "98": "#FFF8F0",
            "99": "#FFFBFF",
            "100": "#FFFFFF"
        },
        "tertiary": {
            "0": "#000000",
            "5": "#011506",
            "10": "#09200F",
            "15": "#142A19",
            "20": "#1F3523",
            "25": "#2A412D",
            "30": "#354C38",
            "35": "#405843",
            "40": "#4C644F",
            "50": "#647D66",
            "60": "#7D977F",
            "70": "#98B299",
            "80": "#B3CDB3",
            "90": "#CEEACE",
            "95": "#DCF8DC",
            "98": "#EAFFE9",
            "99": "#F5FFF2",
            "100": "#FFFFFF"
        },
        "neutral": {
            "0": "#000000",
            "5": "#12110D",
            "10": "#1D1B17",
            "15": "#282521",
            "20": "#33302B",
            "25": "#3E3B36",
            "30": "#494641",
            "35": "#55524D",
            "40": "#615E58",
            "50": "#7A7671",
            "60": "#94908A",
            "70": "#AFAAA4",
            "80": "#CBC6BF",
            "90": "#E8E2DA",
            "95": "#F6F0E8",
            "98": "#FFF8F1",
            "99": "#FFFBFF",
            "100": "#FFFFFF"
        },
        "neutral-variant": {
            "0": "#000000",
            "5": "#141108",
            "10": "#1F1B12",
            "15": "#29251C",
            "20": "#343026",
            "25": "#3F3B31",
            "30": "#4B463C",
            "35": "#575247",
            "40": "#635E52",
            "50": "#7C766A",
            "60": "#979083",
            "70": "#B2AA9D",
            "80": "#CDC6B7",
            "90": "#EAE2D3",
            "95": "#F8F0E1",
            "98": "#FFF8F0",
            "99": "#FFFBFF",
            "100": "#FFFFFF"
        }
    }
}